README.rst
setup.py
human_dates/__init__.py
human_dates.egg-info/PKG-INFO
human_dates.egg-info/SOURCES.txt
human_dates.egg-info/dependency_links.txt
human_dates.egg-info/not-zip-safe
human_dates.egg-info/top_level.txt