Metadata-Version: 1.0
Name: human-dates
Version: 0.2.0
Summary: Dates for humans
Home-page: https://github.com/jtushman/human_dates
Author: Jonathan Tushman
Author-email: jonathan@zefr.com
License: MIT
Platform: UNKNOWN
